upx_installer/__init__.py
upx_installer/installer.py
upx_installer/data/upx.exe
upx_installer-1.0.0.dist-info/licenses/LICENSE
upx_installer-1.0.0.dist-info/METADATA
upx_installer-1.0.0.dist-info/WHEEL
upx_installer-1.0.0.dist-info/entry_points.txt
upx_installer-1.0.0.dist-info/top_level.txt
upx_installer-1.0.0.dist-info/RECORD
